vhdx_2_zvol/__init__.py
vhdx_2_zvol/main.py
vhdx_2_zvol-0.4.4.4.dist-info/METADATA
vhdx_2_zvol-0.4.4.4.dist-info/WHEEL
vhdx_2_zvol-0.4.4.4.dist-info/entry_points.txt
vhdx_2_zvol-0.4.4.4.dist-info/top_level.txt
vhdx_2_zvol-0.4.4.4.dist-info/RECORD
