Metadata-Version: 2.1
Name: vhdx-2-zvol
Version: 0.4.4.4
Summary: Convert from vhdx to qcow to zvol
Home-page: UNKNOWN
Author: UNKNOWN
Author-email: UNKNOWN
License: UNKNOWN
Platform: UNKNOWN
